{
  "identifier": "2b6rex4k37z0u1e3c6dld:1695395696",
  "title": "end of the world obby",
  "complexity": 3000,
  "format_version": 6,
  "update_timestamp": 1695400410513,
  "creation_timestamp": 1695400410513,
  "data_key": "level_data:2b6rex4k37z0u1e3c6dld:1695395696:1",
  "description": "end of the world complete the obby to save all grab players!",
  "creators": [
    "Winter_VR7"
  ],
  "tags": [
    "ok"
  ],
  "statistics": {
    "total_played": 900,
    "difficulty": 0.36770186335403726,
    "liked": 0.8059071729957806,
    "time": 54.749657770270304
  },
  "creator": "Winter_VR7",
  "change": 0
}