{
  "identifier": "2adps2mxxoc2scx8mlroe:1697900773",
  "title": "The Climbable Mountains",
  "complexity": 1104,
  "format_version": 7,
  "update_timestamp": 1697949573378,
  "creation_timestamp": 1697902312067,
  "data_key": "level_data:2adps2mxxoc2scx8mlroe:1697900773:2",
  "description": "Welcome To The Place I Call The Climbable Mountains.",
  "creators": [
    "CoolWhiten",
    "Moltenvr.2023"
  ],
  "tags": [
    "ok"
  ],
  "statistics": {
    "total_played": 200,
    "difficulty": 0.02857142857142857,
    "liked": 0.5,
    "time": 78.92224
  },
  "creator": "CoolWhiten"
}