{"daily": {"identifier": "29se1u9xlnucffcqgzpp0:1753465618", "title": "The Lorax Movie in grab", "complexity": 2539, "update_timestamp": 1753487796673, "creation_timestamp": 1753475744462, "creators": ["nemepro21"], "tags": ["ok"], "statistics": {"total_played": 2000, "difficulty": 0.47, "liked": 0.82, "time": 67.94, "difficulty_string": "easy"}, "images": {"thumb": {"key": "level_29se1u9xlnucffcqgzpp0_1753465618_1_thumb.png"}}, "iteration": 6, "change": 1900}, "weekly": {"identifier": "2bf8hyynuelajywj9k4n7:1752192925", "title": "GAB4 - RING OF FIRE (BOSSFIGHT)", "complexity": 2502, "update_timestamp": 1752266937915, "creation_timestamp": 1752266937915, "creators": ["Polaris8477", "Gouki330", "francis.jaques.56"], "tags": ["ok"], "statistics": {"total_played": 2500, "difficulty": 0, "liked": 1, "time": 141.47, "difficulty_string": "veryhard"}, "images": {"thumb": {"key": "level_2bf8hyynuelajywj9k4n7_1752192925_1_thumb.png"}}, "change": 0}, "unbeaten": {"identifier": "29wytcje12nmxfatcofke:1732846628", "title": "Speed Surge", "complexity": 2731, "update_timestamp": 1734202978915, "creation_timestamp": 1734041581378, "creators": ["BurningAlpaca"], "tags": ["ok"], "statistics": {"total_played": 3200, "difficulty": 0, "difficulty_string": "impossible", "liked": 0, "time": 100}, "images": {"thumb": {"key": "level_29wytcje12nmxfatcofke_1732846628_1_thumb.png"}}, "iteration": 2, "change": 0}}