{"daily": {"identifier": "29prp534vnw8llkf0v0qm:1718590516", "title": "Sans Undertale (SHOWCASE)", "complexity": 3000, "update_timestamp": 1735963924116, "creation_timestamp": 1718596982205, "creators": ["ForevrGrab"], "tags": ["ok"], "statistics": {"total_played": 1200, "difficulty": 0.33, "liked": 0.81, "time": 16.07, "difficulty_string": "medium"}, "images": {"thumb": {"key": "level_29prp534vnw8llkf0v0qm_1718590516_4_thumb.png"}}, "iteration": 55, "change": 0}, "weekly": {"identifier": "2ao6urm519y3ttg54n20m:1734209904", "title": "/-\\ Such Easy lever (+)", "complexity": 2075, "update_timestamp": 1735085345742, "creation_timestamp": 1735019969051, "creators": ["./YLLF.\\", "jake4831", "GavinLikesBeanz", "Cookie", "loaf123457 And Poggggg FOR THE NAME"], "tags": ["ok"], "statistics": {"total_played": 3500, "difficulty": 0, "liked": 1, "time": 1974.24, "difficulty_string": "veryhard"}, "images": {"thumb": {"key": "level_2ao6urm519y3ttg54n20m_1734209904_1_thumb.png"}}, "iteration": 2, "change": 0}, "unbeaten": {"identifier": "29mu59yo9pbgwqloqhthe:1690745443", "title": "Impossible", "complexity": 229, "update_timestamp": 1722546072852, "creation_timestamp": 1690755852015, "tags": ["ok"], "statistics": {"total_played": 38600, "difficulty": 0, "difficulty_string": "impossible", "liked": 0, "time": 100}, "images": {"thumb": {"key": "level_29mu59yo9pbgwqloqhthe_1690745443_1_thumb.png"}}, "iteration": 3, "creators": ["?"], "change": 100}}