{
  "identifier": "2b2yzpd941bjnswahzx47:1695369984",
  "title": "sareutis ice obby",
  "complexity": 323,
  "format_version": 6,
  "update_timestamp": 1695704778253,
  "creation_timestamp": 1695434321554,
  "data_key": "level_data:2b2yzpd941bjnswahzx47:1695369984:5",
  "description": "Complexity - 327.                                           Contributors - RedAnimates , Fireworksexplode.                Thank you very much Slin for verifying my level, it means alot to me.",
  "creators": [
    "sareuti",
    "RedAnimates"
  ],
  "tags": [
    "ok"
  ],
  "statistics": {
    "total_played": 300,
    "difficulty": 0.05693950177935943,
    "liked": 0.8,
    "time": 95.1495
  },
  "creator": "sareuti"
}