{"daily": {"identifier": "2av6ib57lj9sk9p3njt6h:1744509248", "title": "-G E O D E-", "complexity": 2999, "update_timestamp": 1744516161768, "creation_timestamp": 1744516052272, "creators": ["s0ggyfr0gg", "seamonster14", "francis.jaques.56", "Gouki330"], "tags": ["ok"], "statistics": {"total_played": 75, "difficulty": 0.65, "liked": 0.75, "time": 16.39, "difficulty_string": "easy"}, "images": {"thumb": {"key": "level_2av6ib57lj9sk9p3njt6h_1744509248_1_thumb.png"}}, "iteration": 2, "change": 75}, "weekly": {"identifier": "2a7dx97v4xiepfpmj8gi4:1712788482", "title": "Purgatory Path", "complexity": 2964, "update_timestamp": 1713132465968, "creation_timestamp": 1713132465968, "creators": ["Levi__athan"], "tags": ["ok"], "statistics": {"total_played": 23700, "difficulty": 0, "liked": 1, "time": 154.52, "difficulty_string": "veryhard"}, "images": {"thumb": {"key": "level_2a7dx97v4xiepfpmj8gi4_1712788482_1_thumb.png"}}, "change": 0}, "unbeaten": {"identifier": "29wytcje12nmxfatcofke:1738979228", "title": "Narrow Navigations", "complexity": 1872, "update_timestamp": 1739844295130, "creation_timestamp": 1739844295130, "creators": ["BurningAlpaca"], "tags": ["ok"], "statistics": {"total_played": 800, "difficulty": 0, "difficulty_string": "impossible", "liked": 0, "time": 100}, "images": {"thumb": {"key": "level_29wytcje12nmxfatcofke_1738979228_1_thumb.png"}}, "change": 0}}