{
  "identifier": "2b2yzpd941bjnswahzx47:1693821056",
  "title": "a tree is more peaceful",
  "complexity": 2675,
  "format_version": 6,
  "update_timestamp": 1696476967489,
  "creation_timestamp": 1693876877081,
  "data_key": "level_data:2b2yzpd941bjnswahzx47:1693821056:18",
  "description": "ENTERING SIMULATION 40V5 PLEASE BE PAITENT.",
  "creators": [
    "sareuti",
    "y00hooVr",
    "Kyskyhi",
    "Itz_Alwx"
  ],
  "tags": [
    "ok"
  ],
  "statistics": {
    "total_played": 100,
    "difficulty": 0.6721311475409836,
    "liked": 0.7931034482758621,
    "time": 14.420975121951226
  },
  "creator": "sareuti"
}