[
  {
    "plays": "1034",
    "link": "https://grabvr.quest/levels/viewer?level=29mu59yo9pbgwqloqhthe:1649025859",
    "title": "a test of speed, precision, and endurance",
    "age": "406.1476388888889 days",
    "creators": [
      "littlebeastm8"
    ]
  },
  {
    "plays": "2811",
    "link": "https://grabvr.quest/levels/viewer?level=29mu59yo9pbgwqloqhthe:1661901329",
    "title": "flinging fun",
    "age": "393.1480671296296 days",
    "creators": [
      "littlebeastm8"
    ]
  },
  {
    "plays": "26126",
    "link": "https://grabvr.quest/levels/viewer?level=29mu59yo9pbgwqloqhthe:1658771442",
    "title": "demise",
    "age": "436.3026967592593 days",
    "creators": [
      "littlebeastm8"
    ]
  },
  {
    "plays": "7740",
    "link": "https://grabvr.quest/levels/viewer?level=2aq1hyb2tfiuuqvr9wln1:1677370477",
    "title": "Cold And Hot",
    "age": "220.25541666666666 days",
    "creators": [
      "CraftedFlames"
    ]
  },
  {
    "plays": "30082",
    "link": "https://grabvr.quest/levels/viewer?level=29sgp24f1uorbc6vq8d2k:1667046337",
    "title": ".index's challenge (SKILL ISSUE)",
    "age": "203.71621527777776 days",
    "creators": [
      ".index (NSKC7)"
    ]
  },
  {
    "plays": "507",
    "link": "https://grabvr.quest/levels/viewer?level=29srqtwaq08zzhp3kng3u:1682436656",
    "title": "a gift from satan",
    "age": "132.41328703703704 days",
    "creators": [
      "CoblerB1"
    ]
  },
  {
    "plays": "581",
    "link": "https://grabvr.quest/levels/viewer?level=29l50ea34l4s54rtclzus:1679854344",
    "title": "10 levels of hyper tower 2 (cj edition)",
    "age": "131.3733101851852 days",
    "creators": [
      "cjbeast006",
      "cobler",
      "bwlbuck",
      "convrist",
      "D2whiplash"
    ]
  },
  {
    "plays": "892",
    "link": "https://grabvr.quest/levels/viewer?level=29ngj2xcdlinnuqz0vrw5:1677347202",
    "title": "Colors are FUN",
    "age": "128.51554398148147 days",
    "creators": [
      "Cursedphantom(RMB)",
      "Electricc",
      "Yx4824",
      "Socks-sucks"
    ]
  },
  {
    "plays": "710",
    "link": "https://grabvr.quest/levels/viewer?level=29st9jdcbxxotp0t9d8en:1685660794",
    "title": "Hells Mountains",
    "age": "124.13668981481482 days",
    "creators": [
      "Mystery8281",
      "rougeRunner"
    ]
  },
  {
    "plays": "429",
    "link": "https://grabvr.quest/levels/viewer?level=2b8xxpb13ie10xo6oufdc:1681869746",
    "title": "GRAB Kaizo- Simplifeyed To The Point ",
    "age": "121.19001157407406 days",
    "creators": [
      "Socks",
      "and littlebeastM8"
    ]
  },
  {
    "plays": "820",
    "link": "https://grabvr.quest/levels/viewer?level=29srqtwaq08zzhp3kng3u:1686849797",
    "title": "the blood bath",
    "age": "109.4209375 days",
    "creators": [
      "CoblerB1&OliviA13"
    ]
  },
  {
    "plays": "813",
    "link": "https://grabvr.quest/levels/viewer?level=29srqtwaq08zzhp3kng3u:1686930485",
    "title": "eruption",
    "age": "109.40343750000001 days",
    "creators": [
      "CoblerB1",
      "Ryzx"
    ]
  },
  {
    "plays": "1919",
    "link": "https://grabvr.quest/levels/viewer?level=2ay9po2nzhygd2lov96uh:1685394351",
    "title": "PHASE",
    "age": "109.45847222222223 days",
    "creators": [
      "san8102",
      "Dyght_light",
      "crazysherman2"
    ]
  },
  {
    "plays": "3469",
    "link": "https://grabvr.quest/levels/viewer?level=29mu59yo9pbgwqloqhthe:1687203226",
    "title": "Perplexed",
    "age": "88.40424768518518 days",
    "creators": [
      "by littlebeastm8",
      "thanks to Coblerb1 and Socks-sucks for some help"
    ]
  },
  {
    "plays": "1017",
    "link": "https://grabvr.quest/levels/viewer?level=29gz94k4607v9o0mao537:1689440257",
    "title": "A Samurais Training. Back&white",
    "age": "79.35039351851852 days",
    "creators": [
      "bushbaby124"
    ]
  },
  {
    "plays": "7066",
    "link": "https://grabvr.quest/levels/viewer?level=29mu59yo9pbgwqloqhthe:1690745443",
    "title": "Impossible",
    "age": "66.28282407407407 days",
    "creators": [
      "?"
    ]
  },
  {
    "plays": "916",
    "link": "https://grabvr.quest/levels/viewer?level=29qt9i4e2th1db3i02aqm:1678472260",
    "title": "Otter's fling of pain",
    "age": "62.34128472222222 days",
    "creators": [
      "OtterBoy06 prob .index idk"
    ]
  },
  {
    "plays": "442",
    "link": "https://grabvr.quest/levels/viewer?level=2axkwzh6f43g1regf401p:1691127070",
    "title": "The Accuracy Trials",
    "age": "54.01057870370371 days",
    "creators": [
      "oreo rouguerunner"
    ]
  },
  {
    "plays": "1543",
    "link": "https://grabvr.quest/levels/viewer?level=29vhvl94jvlw4vp4b019y:1678846043",
    "title": "luhmao's Ice City",
    "age": "50.15131944444445 days",
    "creators": [
      "luhmao"
    ]
  },
  {
    "plays": "1199",
    "link": "https://grabvr.quest/levels/viewer?level=29ffxg2ijqxyrgxyy2vjj:1685915259",
    "title": "FROSTYs ascent to space!",
    "age": "43.98761574074074 days",
    "creators": [
      "FROSTY_CROSS"
    ]
  },
  {
    "plays": "590",
    "link": "https://grabvr.quest/levels/viewer?level=2aqj12racvbkdg8ge3ns9:1693694611",
    "title": "coleaaron's Only Up/Difficulty Chart V1",
    "age": "22.154409722222223 days",
    "creators": [
      "coleaaron"
    ]
  },
  {
    "plays": "766",
    "link": "https://grabvr.quest/levels/viewer?level=2ay9po2nzhygd2lov96uh:1678056747",
    "title": "7 towers",
    "age": "18.53039351851852 days",
    "creators": [
      "san8102"
    ]
  },
  {
    "plays": "418",
    "link": "https://grabvr.quest/levels/viewer?level=29v9vd6n9z45d16mi2o2n:1695259319",
    "title": "PAIN (jeffbob's skill issue)",
    "age": "11.63267361111111 days",
    "creators": [
      "jeffbob",
      "jp_brady",
      "lowkeyvrpro",
      "NSKC7/index",
      "cy eey"
    ]
  },
  {
    "plays": "451",
    "link": "https://grabvr.quest/levels/viewer?level=2ap0yu9y9g2lcvxbc5x3g:1695778445",
    "title": "Alexs set of skills V4",
    "age": "5.887152777777778 days",
    "creators": [
      "Itz_Alwx FitArtist",
      "Moltenvr",
      "Oliver-M",
      "MrPiglett",
      "hargrave",
      "sareuti"
    ]
  },
  {
    "plays": "408",
    "link": "https://grabvr.quest/levels/viewer?level=2b177hao1rzgp5hlnw0ki:1692586185",
    "title": "LAVA INSANITY",
    "age": "4.691851851851852 days",
    "creators": [
      "Willi_2009 Cursedphantom Monkeyboy"
    ]
  }
]